ydocr/__init__.py
ydocr/predict_system.py
ydocr/predict_table.py
ydocr/utility.py
ydocr/cls/__init__.py
ydocr/cls/postprocess.py
ydocr/cls/predict_cls.py
ydocr/det/__init__.py
ydocr/det/postprocess.py
ydocr/det/predict_det.py
ydocr/det/preprocess.py
ydocr/model/ch_PP-OCRv2_rec_infer.onnx
ydocr/model/ch_PP-OCRv3_det_infer.onnx
ydocr/model/cls-model.onnx
ydocr/model/ppocr_keys_v1.txt
ydocr/model/table_model_ch.onnx
ydocr/model/table_structure_dict_ch.txt
ydocr/rec/__init__.py
ydocr/rec/predict_rec.py
ydocr/rec/rec_decoder.py
ydocr/structure/__init__.py
ydocr/structure/matcher.py
ydocr/structure/postprocess.py
ydocr/structure/predict_structure.py
ydocr/structure/preprocess.py
ydocr/structure/tablepyxl/__init__.py
ydocr/structure/tablepyxl/style.py
ydocr/structure/tablepyxl/tablepyxl.py
ydocr-1.2.8.dist-info/LICENSE
ydocr-1.2.8.dist-info/METADATA
ydocr-1.2.8.dist-info/WHEEL
ydocr-1.2.8.dist-info/top_level.txt
ydocr-1.2.8.dist-info/RECORD
