Metadata-Version: 2.1
Name: ydocr
Version: 1.2.8
Summary: 影刀离线OCR
Home-page: https://github.com/mingo-doer/ydocr
Author: jiaer
Author-email: jia.er@winrobot360.com
License: Apache 2.0
Classifier: Development Status :: 4 - Beta
Classifier: Operating System :: OS Independent
Classifier: Intended Audience :: Developers
Classifier: License :: OSI Approved :: Apache Software License
Classifier: Programming Language :: Python :: 3
Classifier: Topic :: Scientific/Engineering :: Artificial Intelligence
License-File: LICENSE
Requires-Dist: onnxruntime
Requires-Dist: numpy
Requires-Dist: opencv-python
Requires-Dist: shapely
Requires-Dist: pyclipper
Requires-Dist: pillow
Requires-Dist: requests
Requires-Dist: urllib3
Requires-Dist: six
